README.rst
setup.py
lipschitz/__init__.py
lipschitz.egg-info/PKG-INFO
lipschitz.egg-info/SOURCES.txt
lipschitz.egg-info/dependency_links.txt
lipschitz.egg-info/requires.txt
lipschitz.egg-info/top_level.txt
lipschitz/data_loader/__init__.py
lipschitz/data_loader/factor.py
lipschitz/data_loader/interval.py
lipschitz/data_loader/interval_generator.py
lipschitz/data_loader/loader.py
lipschitz/data_loader/utils.py
lipschitz/pipeline/__init__.py
lipschitz/pipeline/backtest/__init__.py
lipschitz/pipeline/backtest/backtest.py
lipschitz/pipeline/backtest/execution_cost.py
lipschitz/pipeline/backtest/transaction_cost.py
lipschitz/pipeline/backtest/utils.py
lipschitz/pipeline/backtest/analyzers/__init__.py
lipschitz/pipeline/backtest/analyzers/analyzer.py
lipschitz/pipeline/backtest/analyzers/sharpe.py
lipschitz/pipeline/backtest/visualization/SimHei.ttf
lipschitz/pipeline/backtest/visualization/__init__.py
lipschitz/pipeline/backtest/visualization/indice_commodity.xlsx
lipschitz/pipeline/backtest/visualization/indice_equity.xlsx
lipschitz/pipeline/backtest/visualization/visualization.py
lipschitz/strategies/__init__.py
lipschitz/strategies/decision_tree.py
lipschitz/strategies/dummy_strategy.py
lipschitz/strategies/strategy_interface.py
lipschitz/strategies/svm.py