Metadata-Version: 2.1
Name: lipschitz
Version: 0.0.1.7
Summary: We envision Lipschitz to be an efficient and precise system for quantitative trading. While being sophisticated in functionalities, Lipschitz remains to be clear, friendly, and robust in its architecture design.
Home-page: https://github.com/LipschitzProject/lipschitz/tree/master
Author: lipschitz
Author-email: andyxukq@gmail.com
License: UNKNOWN
Keywords: trading,development
Platform: UNKNOWN
Classifier: Development Status :: 3 - Alpha
Classifier: Programming Language :: Python :: 3.8
Classifier: Operating System :: OS Independent
Classifier: Topic :: Office/Business :: Financial
Classifier: Topic :: Software Development
